[
    {
    "img"   : "https://mantra4u.shop/cdn/shop/files/LordNarasimhafrontimage.jpg?v=1712117071",
    "name"  : "Lord Narasimha Murti Commemorative Launch",
    "link"  : "https://mantra4u.shop/collections/narasimha-collection/products/lord-narasimha-murti-commemorative-launch/?ref=2",
    "price" : "₹ 18,900.00"
    },
    {
    "img"   : "https://artsofdevotion.com/cdn/shop/files/CloseupfrontImage.jpg?v=1754819039&width=360",
    "name"  : "Yoga Narasimha Murti",
    "link"  : "https://artsofdevotion.com/products/yoga-narasimha-murti",
    "price" : "₹ 77,500.00"
    },
    {
    "img"   : "https://artsofdevotion.com/cdn/shop/files/Side2_cde1fa0e-cb94-4cc9-8afe-a9ff668282f0.jpg?v=1754818997&width=360",
    "name"  : "Laxmi Narasimha 1",
    "link"  : "https://artsofdevotion.com/products/laxmi-narasimha-1",
    "price" : "₹ 32,800.00"
    },
    {
    "img"   : "https://mantra4u.shop/cdn/shop/files/NarasimhaDice1.jpg?v=1715200376",
    "name"  : "Narasimha Kavacha Dice Charms Bracelet",
    "link"  : "https://mantra4u.shop/collections/narasimha-collection/products/narasimha-kavacha-dice-charms-bracelet/?ref=2",
    "price" : "₹ 22,500.00"
    },
    {
    "img"   : "https://mantra4u.shop/cdn/shop/products/20201015_234949.jpg?v=1713288951",
    "name"  : "Lord Narasimha Pendant With Precious Stone",
    "link"  : "https://mantra4u.shop/collections/narasimha-collection/products/lord-narasimha-pendant-with-precious-stone/?ref=2",
    "price" : "₹ 5,665.00"
    },
    {
    "img"   : "https://mantra4u.shop/cdn/shop/products/LordNarasimhaEngraved108E-front.jpg?v=1657987286",
    "name"  : "Lord Narasimha Engraved Mantra Pendant",
    "link"  : "https://mantra4u.shop/collections/narasimha-collection/products/lord-narasimha-engraved-mantra-pendant/?ref=2",
    "price" : "₹ 6,644.00"
    },
    {
    "img"   : "https://mantra4u.shop/cdn/shop/files/NarasimhaCharm1.jpg?v=1715198839",
    "name"  : "Narasimha Kavacha Charms Bracelet",
    "link"  : "https://mantra4u.shop/collections/narasimha-collection/products/narasimha-kavacha-charms-bracelet/?ref=2",
    "price" : "₹ 20,500.00"
    },
    {
    "img"   : "https://artsofdevotion.com/cdn/shop/files/FrontfacingfaceinfocusyogaNarasimha.jpg?v=1754819211&width=360",
    "name"  : "Yoga Narasimha",
    "link"  : "https://artsofdevotion.com/products/yoga-narasimha",
    "price" : "₹ 4,500.00"
    },
    {
    "img"   : "https://artsofdevotion.com/cdn/shop/files/ShantaMukhaNarasimhaLarge_26d18e8d-38f7-4336-a604-1105a26bc79b.jpg?v=1754819241&width=360",
    "name"  : "Shanta Mukha Narasimha",
    "link"  : "https://artsofdevotion.com/products/shanta-mukha-narasimha",
    "price" : "₹ 4,200.00"
    },
    {
    "img"   : "https://artsofdevotion.com/cdn/shop/files/Layingdownppiece.jpg?v=1754819217&width=360",
    "name"  : "Chakra Narasimha",
    "link"  : "https://artsofdevotion.com/products/chakra-narasimha",
    "price" : "₹ 7,700.00"
    },
    {
    "img"   : "https://artsofdevotion.com/cdn/shop/files/FrontImageboth.jpg?v=1754819125&width=360",
    "name"  : "Mayapur Narasimha",
    "link"  : "https://artsofdevotion.com/products/mayapur-narasimha",
    "price" : "₹ 6,050.00"
    },
    {
    "img"   : "https://artsofdevotion.com/cdn/shop/files/LargeShantaAnantanarasimha.jpg?v=1754819113&width=360",
    "name"  : "Shanta Ananta Narasimha",
    "link"  : "https://artsofdevotion.com/products/shanta-ananta-narasimha",
    "price" : "₹ 2,900.00"
    },
    {
    "img"   : "https://artsofdevotion.com/cdn/shop/files/GoldPlatedChakranarasimhaInhand.jpg?v=1754819148&width=360",
    "name"  : "Gold Plated Chakra Narasimha",
    "link"  : "https://artsofdevotion.com/products/gold-plated-chakra-narasimha",
    "price" : "₹ 10,000.00"
    },
    {
    "img"   : "https://artsofdevotion.com/cdn/shop/files/OnlyLargeYoganandaMukha.jpg?v=1754819215&width=360",
    "name"  : "Yogananda",
    "link"  : "https://artsofdevotion.com/products/yogananda",
    "price" : "₹ 4,700.00"
    },
    {
    "img"   : "https://artsofdevotion.com/cdn/shop/files/ClassicNarasimhaInhandsmall.jpg?v=1754819229&width=360",
    "name"  : "Narasimha Pendant 1",
    "link"  : "https://artsofdevotion.com/products/narasimha-pendant-1",
    "price" : "₹ 2,100.00"
    },
    {
    "img"   : "https://artsofdevotion.com/cdn/shop/files/SingleImageontheright.jpg?v=1754819073&width=360",
    "name"  : "Chola Narasimha",
    "link"  : "https://artsofdevotion.com/products/chola-narasimha",
    "price" : "₹ 2,400.00"
    },
    {
    "img"   : "https://artsofdevotion.com/cdn/shop/files/Layingdown_7a69b17a-9b53-4f5a-853a-fd9d21cd644c.jpg?v=1754819110&width=360",
    "name"  : "Classic Laxmi Narasimha",
    "link"  : "https://artsofdevotion.com/products/classic-laxmi-narasimha",
    "price" : "₹ 10,000.00"
    },
    {
    "img"   : "https://artsofdevotion.com/cdn/shop/files/LargePieceonly.jpg?v=1754819194&width=360",
    "name"  : "Plated Shanta Mukha Narasimha",
    "link"  : "https://artsofdevotion.com/products/plated-shanta-mukha-narasimha",
    "price" : "₹ 6,000.00"
    },
    {
    "img"   : "https://artsofdevotion.com/cdn/shop/files/Largepiecesolo.jpg?v=1754819234&width=360",
    "name"  : "Prana Narasimha",
    "link"  : "https://artsofdevotion.com/products/prana-narasimha",
    "price" : "₹ 2,250.00"
    },
    {
    "img"   : "https://artsofdevotion.com/cdn/shop/files/Inhandfrontfacing_ad53a45a-a068-48fa-9c7e-6ea3ad81e652.jpg?v=1754819038&width=360",
    "name"  : "Yoga Narasimha Style 2",
    "link"  : "https://artsofdevotion.com/products/yoga-narasimha-style-2",
    "price" : "₹ 7,500.00"
    },
    {
    "img"   : "https://artsofdevotion.com/cdn/shop/files/Laying.jpg?v=1754819118&width=360",
    "name"  : "Gold Plated Laxmi Narasimha",
    "link"  : "https://artsofdevotion.com/products/gold-plated-laxmi-narasimha",
    "price" : "₹ 10,800.00"
    },
    {
    "img"   : "https://artsofdevotion.com/cdn/shop/files/PrahladNarasimha_SIMG_4x5_d75dc2f8-ba89-40b5-9f22-dc5c82dc759c.jpg?v=1754818992&width=360",
    "name"  : "Prahlad Narasimha",
    "link"  : "https://artsofdevotion.com/products/prahlad-narasimha",
    "price" : "₹ 8,800.00"
    },
    {
    "img"   : "https://artsofdevotion.com/cdn/shop/files/Largepiece.jpg?v=1754819186&width=360",
    "name"  : "Gold Plated Shanta Mukha",
    "link"  : "https://artsofdevotion.com/products/gold-plated-shanta-mukha",
    "price" : "₹ 5,200.00"
    },
    {
    "img"   : "https://artsofdevotion.com/cdn/shop/files/EnameledAnantaNarasimha_v2_LPO.jpg?v=1754819218&width=360",
    "name"  : "Enameled Ananta Narasimha",
    "link"  : "https://artsofdevotion.com/products/enameled-ananta-narasimha",
    "price" : "₹ 3,600.00"
    },
    {
    "img"   : "https://artsofdevotion.com/cdn/shop/files/BothCorrected.jpg?v=1754819133&width=360",
    "name"  : "Plated Yogananda Narasimha",
    "link"  : "https://artsofdevotion.com/products/plated-yogananda-narasimha",
    "price" : "₹ 10,000.00"
    },
    {
    "img"   : "https://artsofdevotion.com/cdn/shop/files/Layingdown_1ff125ec-6a1d-4e41-9d03-332a2566fd52.jpg?v=1754819146&width=360",
    "name"  : "Gold Plated Yogananda Mukha Narasimha",
    "link"  : "https://artsofdevotion.com/products/gold-plated-yogananda-mukha-narasimha",
    "price" : "₹ 10,300.00"
    },
    {
    "img"   : "https://artsofdevotion.com/cdn/shop/files/Layingdown_17fa5061-a15a-4550-b4c1-5c25aaf5aa73.jpg?v=1754819208&width=360",
    "name"  : "Plated Chakra Narasimha",
    "link"  : "https://artsofdevotion.com/products/plated-chakra-narasimha",
    "price" : "₹ 16,900.00"
    },
    {
    "img"   : "https://artsofdevotion.com/cdn/shop/files/Layingdown_13dfe414-3a17-41f0-9876-115be9da8cba.jpg?v=1754818995&width=360",
    "name"  : "Radiant Ananta Narasimha",
    "link"  : "https://artsofdevotion.com/products/radiant-ananta-narasimha",
    "price" : "₹ 7,000.00"
    },
    {
    "img"   : "https://artsofdevotion.com/cdn/shop/files/Side2_cde1fa0e-cb94-4cc9-8afe-a9ff668282f0.jpg?v=1754818997&width=360",
    "name"  : "Laxmi Narasimha 1",
    "link"  : "https://artsofdevotion.com/products/laxmi-narasimha-1",
    "price" : "₹ 32,800.00"
    },
    {
    "img"   : "https://artsofdevotion.com/cdn/shop/files/Inhand_45eb573a-4650-429f-bca7-6c69f29b3b67.jpg?v=1754819149&width=360",
    "name"  : "Gold Plated Classic Narasimha",
    "link"  : "https://artsofdevotion.com/products/gold-plated-classic-narasimha",
    "price" : "₹ 4,000.00"
    },
    {
    "img"   : "https://artsofdevotion.com/cdn/shop/files/InhandLargepiece_0d52ac61-0978-4627-8574-04c6fbb8e1d2.jpg?v=1754819117&width=360",
    "name"  : "Radiant Plated Yogananda Mukha Narasimha",
    "link"  : "https://artsofdevotion.com/products/radiant-plated-yogananda-mukha-narasimha",
    "price" : "₹ 17,000.00"
    },
    {
    "img"   : "https://artsofdevotion.com/cdn/shop/files/Inhand_bfb3961a-5cb1-4602-aae7-83f196fb30ee.jpg?v=1754819102&width=360",
    "name"  : "Ananta Veera Narasimha",
    "link"  : "https://artsofdevotion.com/products/ananta-veera-narasimha",
    "price" : "₹ 8,800.00"
    },
    {
    "img"   : "https://artsofdevotion.com/cdn/shop/files/12.jpg?v=1754819239&width=360",
    "name"  : "Narasimha Ring",
    "link"  : "https://artsofdevotion.com/products/narasimha-ring",
    "price" : "₹ 6,900.00"
    }
]